ender_ansi/__init__.py
ender_ansi/ender_ansi.py
ender_ansi/main.py
ender_ansi-1.0.5.dist-info/LICENSE
ender_ansi-1.0.5.dist-info/METADATA
ender_ansi-1.0.5.dist-info/WHEEL
ender_ansi-1.0.5.dist-info/top_level.txt
ender_ansi-1.0.5.dist-info/RECORD
