Metadata-Version: 2.1
Name: ender-ansi
Version: 1.0.5
Summary: 🌈 uwu cutesy rainbow text <3 ✨
Home-page: https://github.com/endercat126/ender-ansi/
Author: Endercat126
Project-URL: Source, https://github.com/endercat126/ender-ansi/
Keywords: python,colour,ansi
Classifier: Programming Language :: Python :: 3
License-File: LICENSE
